<?xml version="1.0"?><Shipment><SiteId>SKY2C</SiteId><MessageId>221000396884</MessageId><MessageDateTime>2019-05-20T13:08:51.46-05:00</MessageDateTime><TransactionId>000221020010248</TransactionId><TransactionDateTime>2019-05-20T13:08:51.46-05:00</TransactionDateTime><TransactionSetPurpose>Replace</TransactionSetPurpose><ShipmentType>House</ShipmentType><ShipmentStatus>HBL Printed</ShipmentStatus><FileNumber>103004873-01</FileNumber><HouseBillNumber>103004873-01</HouseBillNumber><BookingNumber>RICVD9688900</BookingNumber><Division>10</Division><ControllingDivision>00</ControllingDivision><BusinessLine>30</BusinessLine><Controller>TINA SEMPREVIO</Controller><PaymentMethod>Prepaid</PaymentMethod><TransportationMethod>Ocean Export</TransportationMethod><VesselName>TEMPANOS</VesselName><VoyageFlightNumber>9216</VoyageFlightNumber><FileOpenDate>2019-03-28</FileOpenDate><CutoffDateTime>2019-05-16T00:00:00</CutoffDateTime><DepartureDateTime>2019-05-23T00:00:00</DepartureDateTime><ArrivalDateTime>2019-06-20T00:00:00</ArrivalDateTime><CountryOfOrigin>US</CountryOfOrigin><UltimateDestination>PK</UltimateDestination><QuantityShipped>1</QuantityShipped><GrossWeight>19055.156</GrossWeight><WeightUnit>KG</WeightUnit><TEU>2</TEU><Parties><Party><PartyType>Account</PartyType><PartyCode>IBACR01</PartyCode><Name>IBA + CRUSA PAKISTAN ACCOUNT</Name><PostalCode>00000</PostalCode><CountryCode>US</CountryCode></Party><Party><PartyType>Shipper</PartyType><PartyCode>SOUIT01</PartyCode><Name>SOUTHEAST IT ASSET RECOVERY LLC</Name><Address1>5215 BEECHAM COURT</Address1><CityName>SUWANEE</CityName><StateOrProvinceCode>GA</StateOrProvinceCode><PostalCode>30024</PostalCode><CountryCode>US</CountryCode></Party><Party><PartyType>Consignee</PartyType><PartyCode>TOTHE17</PartyCode><Name>TO THE ORDER OF BANK ALFALAH ISLAMI</Name><Address1>I.I. CHUNDRIGAR ROAD BRANCH</Address1><CityName>KARACHI</CityName><CountryCode>PK</CountryCode></Party><Party><PartyType>Notify</PartyType><PartyCode>IBAINT01</PartyCode><Name>IBA INTERNATIONAL</Name><Address1>202 BUSINESS   FINANCE CENTER, I.I</Address1><Address2>CHUNDRIGAR ROAD</Address2><CityName>KARACHI</CityName><StateOrProvinceCode>KARACHI</StateOrProvinceCode><PostalCode>74000</PostalCode><CountryCode>PK</CountryCode></Party><Party><PartyType>Carrier</PartyType><PartyCode>OCENET01</PartyCode><Name>OCEAN NETWORK EXPRESS</Name><Address1>8730 STONY POINT PARKWAY</Address1><CityName>RICHMOND</CityName><StateOrProvinceCode>VA</StateOrProvinceCode><PostalCode>23235</PostalCode><CountryCode>US</CountryCode><IdCode>ONEY</IdCode><IdCodeQualifier>SCAC</IdCodeQualifier></Party><Party><PartyType>Forwarder</PartyType><PartyCode>10</PartyCode><Name>SKY2C FREIGHT SYSTEMS, INC</Name><Address1>4221 BUSINESS CENTER DRIVE</Address1><Address2>SUITE 5   6</Address2><CityName>FREMONT</CityName><StateOrProvinceCode>CA</StateOrProvinceCode><PostalCode>94538</PostalCode><CountryCode>US</CountryCode></Party><Party><PartyType>Agent</PartyType><PartyCode>NIBZOH</PartyCode><Name>NIBZOH SOLUTIONS INC.</Name><Address1>SUITE # 414 - 415, (CTC) BLOCK-8</Address1><CityName>CLIFTON</CityName><StateOrProvinceCode>KARACHI</StateOrProvinceCode><CountryCode>PK</CountryCode></Party></Parties><Locations><Location><LocationType>PlaceOfReceipt</LocationType><LocationIdQualifier>UN</LocationIdQualifier><LocationId>USATL</LocationId><LocationName>ATLANTA, GA</LocationName><StateOrProvinceCode>GA</StateOrProvinceCode><CountryCode>US</CountryCode></Location><Location><LocationType>PortOfLoad</LocationType><LocationIdQualifier>UN</LocationIdQualifier><LocationId>USCHS</LocationId><LocationName>CHARLESTON, SC</LocationName><StateOrProvinceCode>SC</StateOrProvinceCode><CountryCode>US</CountryCode></Location><Location><LocationType>PortOfDischarge</LocationType><LocationIdQualifier>UN</LocationIdQualifier><LocationId>PKBQM</LocationId><LocationName>PORT QASIM</LocationName><CountryCode>PK</CountryCode></Location></Locations><Containers><Container><EquipmentInitial>GLDU</EquipmentInitial><EquipmentNumber>9343362</EquipmentNumber><SealNumber1>15324460</SealNumber1><EquipmentTypeCode>45G0</EquipmentTypeCode><QuantityShipped>1</QuantityShipped><GrossWeight>19055.156</GrossWeight><WeightUnit>KG</WeightUnit><Contents><Content><QuantityShipped>1</QuantityShipped><Description>PACKED IN 21 PALLETS   USED COMPUTER CPU   LCD  MONITOR, ALONG WITH KEYBOARDS    MOUSE  H.S. CODE: 8471.9090  COUNTRY OF ORIGIN: U.S.A</Description><GrossWeight>19055.156</GrossWeight><WeightUnit>KG</WeightUnit><ScheduleBNumber>8471300100</ScheduleBNumber><QuantityPackagingUnits>0</QuantityPackagingUnits></Content></Contents></Container></Containers><MarksNumbers>GLDU9343362 15324460</MarksNumbers></Shipment>